[
  {
    "id": "1",
    "name": "Fernando",
    "whatsapp": "447380130647",
    "court": "New River Lesiure Centre",
    "coords": [51.60500771371354, -0.09923735582271752],
    "level": "advanced",
    "availability": "周末 or 平日下班後",
    "moreInfo": "每周打 1-2 次"
  },
  {
    "id": "2",
    "name": "Ryan",
    "whatsapp": "447526540994",
    "court": "Regent's Park Tennis Centre",
    "coords": [51.52577874869013, -0.15371467172520364],
    "level": "advanced",
    "availability": "",
    "moreInfo": ""
  },
  {
    "id": "3",
    "name": "子頤",
    "whatsapp": "447761848043",
    "court": "Stockwell",
    "coords": [51.472346199126996, -0.12289799881983392],
    "level": "improver",
    "availability": "",
    "moreInfo": ""
  },
  {
    "id": "4",
    "name": "Josephine",
    "whatsapp": "447395678080",
    "court": "Sutton",
    "coords": [51.35972126104192, -0.19117216193619174],
    "level": "improver",
    "availability": "",
    "moreInfo": "冬天希望能約室內場"
  }
]
